numeric_edahelper/__init__.py
numeric_edahelper/flag_outliers.py
numeric_edahelper/get_correlated_features.py
numeric_edahelper/missing_imputer.py
numeric_edahelper/overview.py
numeric_edahelper-1.0.7.dist-info/LICENSE
numeric_edahelper-1.0.7.dist-info/WHEEL
numeric_edahelper-1.0.7.dist-info/METADATA
numeric_edahelper-1.0.7.dist-info/RECORD
