Metadata-Version: 2.1
Name: numeric-edahelper
Version: 1.0.7
Summary: Exploratory data analysis package for data that is numeric in nature.
Home-page: https://github.com/UBC-MDS/numeric_edahelper
License: MIT
Author: Samuel Quist
Requires-Python: >=3.9,<4.0
Classifier: License :: OSI Approved :: MIT License
Classifier: Programming Language :: Python :: 3
Classifier: Programming Language :: Python :: 3.10
Classifier: Programming Language :: Python :: 3.9
Requires-Dist: numpy (>=1.22.1,<2.0.0)
Requires-Dist: pandas (>=1.3.5,<2.0.0)
Project-URL: Documentation, https://numeric-edahelper.readthedocs.io
Project-URL: Repository, https://github.com/UBC-MDS/numeric_edahelper
